jamorasep/__init__.py
jamorasep/kana_util.py
jamorasep/main.py
jamorasep/resource/kanamap.csv
jamorasep-0.0.1.dist-info/LICENSE
jamorasep-0.0.1.dist-info/METADATA
jamorasep-0.0.1.dist-info/WHEEL
jamorasep-0.0.1.dist-info/top_level.txt
jamorasep-0.0.1.dist-info/RECORD
