Metadata-Version: 2.1
Name: jamorasep
Version: 0.0.1
Summary: Japanese mora separator
Home-page: https://github.com/tachi-hi/jamorasep
Author: Hideyuki Tachibana
Author-email: h_tachibana@pkshatec.com
License: MIT
Keywords: jpyomi
Classifier: Development Status :: 3 - Alpha
Classifier: Intended Audience :: Science/Research
Classifier: License :: OSI Approved :: MIT License
Classifier: Natural Language :: Japanese
Classifier: Programming Language :: Python :: 3.7
Classifier: Programming Language :: Python :: 3.8
Classifier: Programming Language :: Python :: 3.9
Classifier: Programming Language :: Python :: 3.10
Classifier: Programming Language :: Python :: 3.11
Requires-Python: >=3.5
License-File: LICENSE
Requires-Dist: typeguard
